nominalpy/__init__.py
nominalpy/connection/__init__.py
nominalpy/connection/credentials.py
nominalpy/connection/http_requests.py
nominalpy/data/__init__.py
nominalpy/data/frame.py
nominalpy/maths/__init__.py
nominalpy/maths/astro.py
nominalpy/maths/computer_library.py
nominalpy/maths/constants.py
nominalpy/maths/constellations.py
nominalpy/maths/data.py
nominalpy/maths/kinematics.py
nominalpy/maths/mass.py
nominalpy/maths/sensors.py
nominalpy/maths/utils.py
nominalpy/mqtt/__init__.py
nominalpy/mqtt/client.py
nominalpy/simulation/__init__.py
nominalpy/simulation/behaviour.py
nominalpy/simulation/instance.py
nominalpy/simulation/message.py
nominalpy/simulation/model.py
nominalpy/simulation/object.py
nominalpy/simulation/session.py
nominalpy/simulation/simulation.py
nominalpy/simulation/system.py
nominalpy/utils/__init__.py
nominalpy/utils/exception.py
nominalpy/utils/helper.py
nominalpy/utils/printer.py
nominalpy/utils/types.py
nominalpy-1.2.0.0.dist-info/licenses/LICENSE
nominalpy-1.2.0.0.dist-info/METADATA
nominalpy-1.2.0.0.dist-info/WHEEL
nominalpy-1.2.0.0.dist-info/top_level.txt
nominalpy-1.2.0.0.dist-info/RECORD
