Metadata-Version: 2.4
Name: nominalpy
Version: 1.2.0.0
Summary: Python Interface to the Nominal API for simulations
Home-page: https://github.com/NominalSystems/nominalpy
Author: Nominal Systems
Author-email: support@nominalsys.com
License-File: LICENSE
Requires-Dist: aiohttp
Requires-Dist: urllib3
Requires-Dist: paho-mqtt
Requires-Dist: numpy
Requires-Dist: pandas
Requires-Dist: matplotlib
Requires-Dist: setuptools
Requires-Dist: pytest-asyncio
Requires-Dist: requests
Dynamic: author
Dynamic: author-email
Dynamic: description
Dynamic: home-page
Dynamic: license-file
Dynamic: requires-dist
Dynamic: summary
